cellblender/__init__.py
cellblender/core.py
cellblender-0.1.2.dist-info/licenses/LICENSE
cellblender-0.1.2.dist-info/METADATA
cellblender-0.1.2.dist-info/WHEEL
cellblender-0.1.2.dist-info/top_level.txt
cellblender-0.1.2.dist-info/RECORD
